honeycomb_sqlalchemy.py
honeycomb_sqlalchemy-1.0.0.dist-info/LICENSE
honeycomb_sqlalchemy-1.0.0.dist-info/METADATA
honeycomb_sqlalchemy-1.0.0.dist-info/WHEEL
honeycomb_sqlalchemy-1.0.0.dist-info/top_level.txt
honeycomb_sqlalchemy-1.0.0.dist-info/zip-safe
honeycomb_sqlalchemy-1.0.0.dist-info/RECORD
