Metadata-Version: 2.1
Name: honeycomb-sqlalchemy
Version: 1.0.0
Summary: SQLAlchemy Instrumentation for Honeycomb
Home-page: http://github.com/findpace/honeycomb-sqlalchemy
Author: Pace
Author-email: tech@pacerevenue.com
License: Apache License, Version 2.0
Platform: UNKNOWN
Classifier: Programming Language :: Python
Classifier: Operating System :: MacOS :: MacOS X
Classifier: Operating System :: POSIX
Classifier: Programming Language :: Python :: 3
Classifier: Programming Language :: Python :: 3.6
Classifier: Programming Language :: Python :: 3.7
Classifier: Programming Language :: Python :: 3.8
Classifier: Programming Language :: Python :: 3.9
Classifier: Topic :: Internet
Classifier: Topic :: Software Development :: Libraries :: Python Modules
Classifier: Intended Audience :: Developers
Requires-Dist: honeycomb-beeline
Requires-Dist: sqlalchemy
Provides-Extra: dev
Requires-Dist: coverage (==5.5) ; extra == 'dev'
Requires-Dist: pytest (==6.2.2) ; extra == 'dev'
Requires-Dist: psycopg2-binary (==2.8.6) ; extra == 'dev'
